handyplot/__init__.py
handyplot/color.py
handyplot/contour.py
handyplot/figure.py
handyplot/figure_base.py
handyplot-0.3.6.dist-info/LICENSE
handyplot-0.3.6.dist-info/METADATA
handyplot-0.3.6.dist-info/WHEEL
handyplot-0.3.6.dist-info/top_level.txt
handyplot-0.3.6.dist-info/RECORD
