Metadata-Version: 2.1
Name: handyplot
Version: 0.3.6
Summary: Test.
Home-page: https://github.com/minho-hong/handyplot.git
Author: Hong Peng
License: GPL
Requires-Python: >=3.8.0
License-File: LICENSE
Requires-Dist: matplotlib
Requires-Dist: numpy
Requires-Dist: vtk
